ezDiscord.py
XPHN_ezDiscord-1.5.dist-info/LICENSE
XPHN_ezDiscord-1.5.dist-info/METADATA
XPHN_ezDiscord-1.5.dist-info/WHEEL
XPHN_ezDiscord-1.5.dist-info/top_level.txt
XPHN_ezDiscord-1.5.dist-info/RECORD
