Metadata-Version: 2.1
Name: XPHN-ezDiscord
Version: 1.5
Summary: Easily create and use Discord Webhooks and simple bots.
Home-page: UNKNOWN
Author: Xephonine // Hylaxe
License: UNKNOWN
Platform: UNKNOWN
Classifier: Programming Language :: Python :: 3
Classifier: License :: OSI Approved :: MIT License
Classifier: Operating System :: Android
Classifier: Operating System :: Microsoft
Classifier: Operating System :: Microsoft :: Windows
Classifier: Operating System :: OS Independent
Requires-Python: >=3.2
License-File: LICENSE
Requires-Dist: discord
Requires-Dist: requests
